escaper_utilities/__init__.py
escaper_utilities-1.0.9.dist-info/METADATA
escaper_utilities-1.0.9.dist-info/WHEEL
escaper_utilities-1.0.9.dist-info/top_level.txt
escaper_utilities-1.0.9.dist-info/RECORD
