Metadata-Version: 2.1
Name: escaper-utilities
Version: 1.0.9
Summary: EKAPE_utilities
Home-page: UNKNOWN
Author: sike6054
Author-email: sike6054@gmail.com
License: UNKNOWN
Platform: UNKNOWN
Classifier: Programming Language :: Python :: 3.6
Classifier: Programming Language :: Python :: 3.7
Classifier: Programming Language :: Python :: 3.8
Classifier: Programming Language :: Python :: 3.9
Classifier: Programming Language :: Python :: 3.10
Classifier: License :: OSI Approved :: MIT License
Classifier: Operating System :: OS Independent
Requires-Python: >=3.6, <=3.10
